[
  {
    "inputs": [
      {
        "internalType": "address",
        "name": "_coin",
        "type": "address"
      },
      {
        "internalType": "address",
        "name": "_zether",
        "type": "address"
      },
      {
        "internalType": "address",
        "name": "_burn",
        "type": "address"
      },
      {
        "internalType": "uint256",
        "name": "_epochLength",
        "type": "uint256"
      },
      {
        "internalType": "address",
        "name": "_admin",
        "type": "address"
      },
      {
        "internalType": "address",
        "name": "_authority",
        "type": "address"
      },
      {
        "internalType": "address",
        "name": "dvp",
        "type": "address"
      }
    ],
    "stateMutability": "nonpayable",
    "type": "constructor"
  },
  {
    "anonymous": false,
    "inputs": [
      {
        "indexed": true,
        "internalType": "bytes32",
        "name": "role",
        "type": "bytes32"
      },
      {
        "indexed": true,
        "internalType": "bytes32",
        "name": "previousAdminRole",
        "type": "bytes32"
      },
      {
        "indexed": true,
        "internalType": "bytes32",
        "name": "newAdminRole",
        "type": "bytes32"
      }
    ],
    "name": "RoleAdminChanged",
    "type": "event"
  },
  {
    "anonymous": false,
    "inputs": [
      {
        "indexed": true,
        "internalType": "bytes32",
        "name": "role",
        "type": "bytes32"
      },
      {
        "indexed": true,
        "internalType": "address",
        "name": "account",
        "type": "address"
      },
      {
        "indexed": true,
        "internalType": "address",
        "name": "sender",
        "type": "address"
      }
    ],
    "name": "RoleGranted",
    "type": "event"
  },
  {
    "anonymous": false,
    "inputs": [
      {
        "indexed": true,
        "internalType": "bytes32",
        "name": "role",
        "type": "bytes32"
      },
      {
        "indexed": true,
        "internalType": "address",
        "name": "account",
        "type": "address"
      },
      {
        "indexed": true,
        "internalType": "address",
        "name": "sender",
        "type": "address"
      }
    ],
    "name": "RoleRevoked",
    "type": "event"
  },
  {
    "anonymous": false,
    "inputs": [
      {
        "components": [
          {
            "internalType": "bytes32",
            "name": "x",
            "type": "bytes32"
          },
          {
            "internalType": "bytes32",
            "name": "y",
            "type": "bytes32"
          }
        ],
        "indexed": false,
        "internalType": "struct Utils.G1Point[]",
        "name": "parties",
        "type": "tuple[]"
      },
      {
        "components": [
          {
            "internalType": "bytes32",
            "name": "x",
            "type": "bytes32"
          },
          {
            "internalType": "bytes32",
            "name": "y",
            "type": "bytes32"
          }
        ],
        "indexed": false,
        "internalType": "struct Utils.G1Point",
        "name": "beneficiary",
        "type": "tuple"
      }
    ],
    "name": "TransferOccurred",
    "type": "event"
  },
  {
    "inputs": [],
    "name": "DEFAULT_ADMIN_ROLE",
    "outputs": [
      {
        "internalType": "bytes32",
        "name": "",
        "type": "bytes32"
      }
    ],
    "stateMutability": "view",
    "type": "function"
  },
  {
    "inputs": [],
    "name": "REGISTER_ROLE",
    "outputs": [
      {
        "internalType": "bytes32",
        "name": "",
        "type": "bytes32"
      }
    ],
    "stateMutability": "view",
    "type": "function"
  },
  {
    "inputs": [],
    "name": "TRANSFER_ROLE",
    "outputs": [
      {
        "internalType": "bytes32",
        "name": "",
        "type": "bytes32"
      }
    ],
    "stateMutability": "view",
    "type": "function"
  },
  {
    "inputs": [
      {
        "components": [
          {
            "internalType": "bytes32",
            "name": "x",
            "type": "bytes32"
          },
          {
            "internalType": "bytes32",
            "name": "y",
            "type": "bytes32"
          }
        ],
        "internalType": "struct Utils.G1Point",
        "name": "y",
        "type": "tuple"
      },
      {
        "internalType": "uint256",
        "name": "bTransfer",
        "type": "uint256"
      },
      {
        "components": [
          {
            "internalType": "bytes32",
            "name": "x",
            "type": "bytes32"
          },
          {
            "internalType": "bytes32",
            "name": "y",
            "type": "bytes32"
          }
        ],
        "internalType": "struct Utils.G1Point",
        "name": "u",
        "type": "tuple"
      },
      {
        "internalType": "bytes",
        "name": "proof",
        "type": "bytes"
      }
    ],
    "name": "burn",
    "outputs": [],
    "stateMutability": "nonpayable",
    "type": "function"
  },
  {
    "inputs": [],
    "name": "epochLength",
    "outputs": [
      {
        "internalType": "uint256",
        "name": "",
        "type": "uint256"
      }
    ],
    "stateMutability": "view",
    "type": "function"
  },
  {
    "inputs": [],
    "name": "fee",
    "outputs": [
      {
        "internalType": "uint256",
        "name": "",
        "type": "uint256"
      }
    ],
    "stateMutability": "view",
    "type": "function"
  },
  {
    "inputs": [
      {
        "components": [
          {
            "internalType": "bytes32",
            "name": "x",
            "type": "bytes32"
          },
          {
            "internalType": "bytes32",
            "name": "y",
            "type": "bytes32"
          }
        ],
        "internalType": "struct Utils.G1Point",
        "name": "y",
        "type": "tuple"
      },
      {
        "internalType": "uint256",
        "name": "bTransfer",
        "type": "uint256"
      }
    ],
    "name": "fund",
    "outputs": [],
    "stateMutability": "nonpayable",
    "type": "function"
  },
  {
    "inputs": [],
    "name": "getRegsiteredAccounts",
    "outputs": [
      {
        "components": [
          {
            "internalType": "bytes32",
            "name": "name",
            "type": "bytes32"
          },
          {
            "components": [
              {
                "internalType": "bytes32",
                "name": "x",
                "type": "bytes32"
              },
              {
                "internalType": "bytes32",
                "name": "y",
                "type": "bytes32"
              }
            ],
            "internalType": "struct Utils.G1Point",
            "name": "shieldedAddress",
            "type": "tuple"
          }
        ],
        "internalType": "struct ZSCRestricted.Participant[]",
        "name": "",
        "type": "tuple[]"
      }
    ],
    "stateMutability": "view",
    "type": "function"
  },
  {
    "inputs": [
      {
        "internalType": "bytes32",
        "name": "role",
        "type": "bytes32"
      }
    ],
    "name": "getRoleAdmin",
    "outputs": [
      {
        "internalType": "bytes32",
        "name": "",
        "type": "bytes32"
      }
    ],
    "stateMutability": "view",
    "type": "function"
  },
  {
    "inputs": [
      {
        "internalType": "bytes32",
        "name": "role",
        "type": "bytes32"
      },
      {
        "internalType": "address",
        "name": "account",
        "type": "address"
      }
    ],
    "name": "grantRole",
    "outputs": [],
    "stateMutability": "nonpayable",
    "type": "function"
  },
  {
    "inputs": [
      {
        "internalType": "bytes32",
        "name": "role",
        "type": "bytes32"
      },
      {
        "internalType": "address",
        "name": "account",
        "type": "address"
      }
    ],
    "name": "hasRole",
    "outputs": [
      {
        "internalType": "bool",
        "name": "",
        "type": "bool"
      }
    ],
    "stateMutability": "view",
    "type": "function"
  },
  {
    "inputs": [],
    "name": "lastGlobalUpdate",
    "outputs": [
      {
        "internalType": "uint256",
        "name": "",
        "type": "uint256"
      }
    ],
    "stateMutability": "view",
    "type": "function"
  },
  {
    "inputs": [
      {
        "internalType": "bytes32",
        "name": "proofHash",
        "type": "bytes32"
      }
    ],
    "name": "lockProof",
    "outputs": [],
    "stateMutability": "nonpayable",
    "type": "function"
  },
  {
    "inputs": [
      {
        "components": [
          {
            "internalType": "bytes32",
            "name": "x",
            "type": "bytes32"
          },
          {
            "internalType": "bytes32",
            "name": "y",
            "type": "bytes32"
          }
        ],
        "internalType": "struct Utils.G1Point",
        "name": "y",
        "type": "tuple"
      },
      {
        "internalType": "uint256",
        "name": "c",
        "type": "uint256"
      },
      {
        "internalType": "uint256",
        "name": "s",
        "type": "uint256"
      },
      {
        "internalType": "bytes32",
        "name": "name",
        "type": "bytes32"
      }
    ],
    "name": "register",
    "outputs": [],
    "stateMutability": "nonpayable",
    "type": "function"
  },
  {
    "inputs": [
      {
        "internalType": "bytes32",
        "name": "role",
        "type": "bytes32"
      },
      {
        "internalType": "address",
        "name": "account",
        "type": "address"
      }
    ],
    "name": "renounceRole",
    "outputs": [],
    "stateMutability": "nonpayable",
    "type": "function"
  },
  {
    "inputs": [
      {
        "internalType": "bytes32",
        "name": "role",
        "type": "bytes32"
      },
      {
        "internalType": "address",
        "name": "account",
        "type": "address"
      }
    ],
    "name": "revokeRole",
    "outputs": [],
    "stateMutability": "nonpayable",
    "type": "function"
  },
  {
    "inputs": [
      {
        "components": [
          {
            "internalType": "bytes32",
            "name": "x",
            "type": "bytes32"
          },
          {
            "internalType": "bytes32",
            "name": "y",
            "type": "bytes32"
          }
        ],
        "internalType": "struct Utils.G1Point[]",
        "name": "y",
        "type": "tuple[]"
      },
      {
        "internalType": "uint256",
        "name": "epoch",
        "type": "uint256"
      }
    ],
    "name": "simulateAccounts",
    "outputs": [
      {
        "components": [
          {
            "internalType": "bytes32",
            "name": "x",
            "type": "bytes32"
          },
          {
            "internalType": "bytes32",
            "name": "y",
            "type": "bytes32"
          }
        ],
        "internalType": "struct Utils.G1Point[2][]",
        "name": "accounts",
        "type": "tuple[2][]"
      }
    ],
    "stateMutability": "view",
    "type": "function"
  },
  {
    "inputs": [
      {
        "internalType": "bytes4",
        "name": "interfaceId",
        "type": "bytes4"
      }
    ],
    "name": "supportsInterface",
    "outputs": [
      {
        "internalType": "bool",
        "name": "",
        "type": "bool"
      }
    ],
    "stateMutability": "view",
    "type": "function"
  },
  {
    "inputs": [
      {
        "components": [
          {
            "components": [
              {
                "internalType": "bytes32",
                "name": "x",
                "type": "bytes32"
              },
              {
                "internalType": "bytes32",
                "name": "y",
                "type": "bytes32"
              }
            ],
            "internalType": "struct Utils.G1Point[]",
            "name": "C",
            "type": "tuple[]"
          },
          {
            "components": [
              {
                "internalType": "bytes32",
                "name": "x",
                "type": "bytes32"
              },
              {
                "internalType": "bytes32",
                "name": "y",
                "type": "bytes32"
              }
            ],
            "internalType": "struct Utils.G1Point",
            "name": "D",
            "type": "tuple"
          },
          {
            "components": [
              {
                "internalType": "bytes32",
                "name": "x",
                "type": "bytes32"
              },
              {
                "internalType": "bytes32",
                "name": "y",
                "type": "bytes32"
              }
            ],
            "internalType": "struct Utils.G1Point[]",
            "name": "y",
            "type": "tuple[]"
          },
          {
            "components": [
              {
                "internalType": "bytes32",
                "name": "x",
                "type": "bytes32"
              },
              {
                "internalType": "bytes32",
                "name": "y",
                "type": "bytes32"
              }
            ],
            "internalType": "struct Utils.G1Point",
            "name": "u",
            "type": "tuple"
          },
          {
            "internalType": "bytes",
            "name": "proof",
            "type": "bytes"
          },
          {
            "components": [
              {
                "internalType": "bytes32",
                "name": "x",
                "type": "bytes32"
              },
              {
                "internalType": "bytes32",
                "name": "y",
                "type": "bytes32"
              }
            ],
            "internalType": "struct Utils.G1Point",
            "name": "beneficiary",
            "type": "tuple"
          }
        ],
        "internalType": "struct ZetherVerifier.Transaction",
        "name": "transaction",
        "type": "tuple"
      }
    ],
    "name": "transfer",
    "outputs": [
      {
        "internalType": "bool",
        "name": "",
        "type": "bool"
      }
    ],
    "stateMutability": "nonpayable",
    "type": "function"
  }
]
